reuse/__init__.py
reuse/__main__.py
reuse/_annotate.py
reuse/_licenses.py
reuse/_util.py
reuse/cli/__init__.py
reuse/cli/annotate.py
reuse/cli/common.py
reuse/cli/convert_dep5.py
reuse/cli/download.py
reuse/cli/lint.py
reuse/cli/lint_file.py
reuse/cli/main.py
reuse/cli/spdx.py
reuse/cli/supported_licenses.py
reuse/comment.py
reuse/convert_dep5.py
reuse/copyright.py
reuse/covered_files.py
reuse/download.py
reuse/exceptions.py
reuse/extract.py
reuse/global_licensing.py
reuse/header.py
reuse/i18n.py
reuse/lint.py
reuse/locale/aln/LC_MESSAGES/reuse.mo
reuse/locale/cs/LC_MESSAGES/reuse.mo
reuse/locale/de/LC_MESSAGES/reuse.mo
reuse/locale/eo/LC_MESSAGES/reuse.mo
reuse/locale/es/LC_MESSAGES/reuse.mo
reuse/locale/fr/LC_MESSAGES/reuse.mo
reuse/locale/gl/LC_MESSAGES/reuse.mo
reuse/locale/it/LC_MESSAGES/reuse.mo
reuse/locale/ja/LC_MESSAGES/reuse.mo
reuse/locale/nl/LC_MESSAGES/reuse.mo
reuse/locale/pt/LC_MESSAGES/reuse.mo
reuse/locale/ru/LC_MESSAGES/reuse.mo
reuse/locale/sq/LC_MESSAGES/reuse.mo
reuse/locale/sv/LC_MESSAGES/reuse.mo
reuse/locale/tr/LC_MESSAGES/reuse.mo
reuse/locale/uk/LC_MESSAGES/reuse.mo
reuse/locale/zh_Hant/LC_MESSAGES/reuse.mo
reuse/project.py
reuse/py.typed
reuse/report.py
reuse/resources/exceptions.json
reuse/resources/exceptions.json.license
reuse/resources/licenses.json
reuse/resources/licenses.json.license
reuse/templates/default_template.jinja2
reuse/templates/default_template.jinja2.license
reuse/types.py
reuse/vcs.py
reuse-6.1.2.dist-info/AUTHORS.rst
reuse-6.1.2.dist-info/LICENSES/Apache-2.0.txt
reuse-6.1.2.dist-info/LICENSES/CC-BY-SA-4.0.txt
reuse-6.1.2.dist-info/LICENSES/CC0-1.0.txt
reuse-6.1.2.dist-info/LICENSES/GPL-3.0-or-later.txt
reuse-6.1.2.dist-info/METADATA
reuse-6.1.2.dist-info/WHEEL
reuse-6.1.2.dist-info/entry_points.txt
reuse-6.1.2.dist-info/RECORD
