Metadata-Version: 2.1
Name: reuse
Version: 6.1.2
Summary: reuse is a tool for compliance with the REUSE recommendations.
Home-page: https://reuse.software/
License: Apache-2.0 AND CC0-1.0 AND CC-BY-SA-4.0 AND GPL-3.0-or-later
Author: Free Software Foundation Europe
Author-email: contact@fsfe.org
Maintainer: Carmen Bianca Bakker
Maintainer-email: carmenbianca@fsfe.org
Requires-Python: >=3.10
Classifier: Development Status :: 5 - Production/Stable
Classifier: Intended Audience :: Developers
Classifier: License :: CC0 1.0 Universal (CC0 1.0) Public Domain Dedication
Classifier: License :: DFSG approved
Classifier: License :: OSI Approved
Classifier: License :: OSI Approved :: Apache Software License
Classifier: License :: OSI Approved :: GNU General Public License v3 or later (GPLv3+)
Classifier: License :: Other/Proprietary License
Classifier: Programming Language :: Python :: 3
Classifier: Programming Language :: Python :: 3.10
Classifier: Programming Language :: Python :: 3.11
Classifier: Programming Language :: Python :: 3.12
Classifier: Programming Language :: Python :: 3.13
Provides-Extra: chardet
Provides-Extra: charset-normalizer
Requires-Dist: Jinja2 (>=3.0.0)
Requires-Dist: attrs (>=23.2)
Requires-Dist: chardet (>=3.0.2) ; extra == "chardet"
Requires-Dist: charset-normalizer (>=2.0.5) ; extra == "charset-normalizer"
Requires-Dist: click (>=8.1)
Requires-Dist: license-expression (>=21.6.14)
Requires-Dist: python-debian (>=0.1.48)
Requires-Dist: python-magic (>=0.4.12)
Requires-Dist: tomlkit (>=0.8)
Project-URL: Documentation, https://reuse.readthedocs.org/
Project-URL: Repository, https://github.com/fsfe/reuse-tool
